dockside/__init__.py
dockside/io.py
dockside/nwis.py
dockside/tests/__init__.py
dockside/tests/test_io.py
dockside/tests/test_nwis.py
dockside/tests/util.py
dockside-0.1.2.dist-info/LICENSE
dockside-0.1.2.dist-info/METADATA
dockside-0.1.2.dist-info/WHEEL
dockside-0.1.2.dist-info/top_level.txt
dockside-0.1.2.dist-info/RECORD
